ipsvm/__init__.py
ipsvm/config.py
ipsvm/data.py
ipsvm/default.json
ipsvm/ipsvm.py
ipsvm/predictor.pkl
ipsvm/shock.py
ipsvm-1.2.1.dist-info/METADATA
ipsvm-1.2.1.dist-info/WHEEL
ipsvm-1.2.1.dist-info/top_level.txt
ipsvm-1.2.1.dist-info/RECORD
