Metadata-Version: 2.1
Name: ipsvm
Version: 1.2.1
Summary: Machine learning algorithm for detection of interplanetary shock waves
Home-page: https://bitbucket.org/raysofspace/ipsvm
Author: Rays of Space Oy
Author-email: info@raysofspace.com
License: MIT
Requires-Dist: ai.cdas ==1.2.3
Requires-Dist: astropy ==6.0.1
Requires-Dist: joblib ==1.3.2
Requires-Dist: matplotlib ==3.8.3
Requires-Dist: numpy ==1.26.4
Requires-Dist: pandas ==2.2.1
Requires-Dist: PyPrind ==2.11.3
Requires-Dist: python-dateutil ==2.9.0
Requires-Dist: scikit-learn ==1.4.2
